cperms/__init__.py
cperms/av.py
cperms/cayley.py
Cayley_perms-1.0.dist-info/METADATA
Cayley_perms-1.0.dist-info/WHEEL
Cayley_perms-1.0.dist-info/top_level.txt
Cayley_perms-1.0.dist-info/RECORD
