Metadata-Version: 2.2
Name: Cayley_perms
Version: 1.0
Summary: A module for using Cayley permutations.
Dynamic: summary
